<?xml version="1.0" encoding="utf-8" ?>
<dwsync>
<file name="glasses.jpg" server="ftp.infocusadv.com" local="130909980935955267" remote="130904619000000000" Dst="1" />
<file name="logo.png" server="ftp.infocusadv.com" local="130909980935674998" remote="130904540400000000" Dst="1" />
<file name="glasses2.jpg" server="ftp.infocusadv.com" local="130909980935344679" remote="130906345200000000" Dst="1" />
<file name="062315_corbenCompShorter_v2.png" server="ftp.infocusadv.com" local="130928216531309763" remote="130927830000000000" Dst="1" />
<file name="glasses-bg.png" server="ftp.infocusadv.com" local="130928216532800354" remote="130927830000000000" Dst="1" />
<file name="contact-info-bg.jpg" server="ftp.infocusadv.com" local="130929709538484454" remote="130929593400000000" Dst="1" />
<file name="glasses-blue.svg" server="ftp.infocusadv.com" local="130929710078797925" remote="130928305800000000" Dst="1" />
<file name="glasses.png" server="ftp.infocusadv.com" local="130929710084554730" remote="130928305800000000" Dst="1" />
<file name=".DS_Store" server="ftp.bennettcodes.com" local="130934379269413354" remote="130934016600000000" Dst="1" />
<file name="062315_corbenCompShorter_v2.png" server="ftp.bennettcodes.com" local="130934379270490017" remote="130934016600000000" Dst="1" />
<file name="comp5.png" server="ftp.bennettcodes.com" local="130934379338497269" remote="130934020200000000" Dst="1" />
<file name="contact-info-bg.jpg" server="ftp.bennettcodes.com" local="130934379340207509" remote="130934016600000000" Dst="1" />
<file name="glasses-bg.png" server="ftp.bennettcodes.com" local="130934379351882605" remote="130934016600000000" Dst="1" />
<file name="glasses-black.svg" server="ftp.bennettcodes.com" local="130934379351742571" remote="130934020200000000" Dst="1" />
<file name="glasses-blue.svg" server="ftp.bennettcodes.com" local="130934379352902874" remote="130934016600000000" Dst="1" />
<file name="glasses.jpg" server="ftp.bennettcodes.com" local="130934379355815330" remote="130934016600000000" Dst="1" />
<file name="glasses.png" server="ftp.bennettcodes.com" local="130934379354897941" remote="130934016600000000" Dst="1" />
<file name="logo.png" server="ftp.bennettcodes.com" local="130934379361510654" remote="130934016600000000" Dst="1" />
<file name="glasses2.jpg" server="ftp.bennettcodes.com" local="130934379358768585" remote="130934016600000000" Dst="1" />
<file name="ajax-loader.gif" server="ftp.bennettcodes.com" local="130934379271883446" remote="130934020200000000" Dst="1" />
<file name="loading.gif" server="ftp.bennettcodes.com" local="130934379359308716" remote="130934020200000000" Dst="1" />
<file name="loading.svg" server="ftp.bennettcodes.com" local="130934379359108852" remote="130934020200000000" Dst="1" />
<file name="perfect-pair-bg-temp.jpg" server="ftp.bennettcodes.com" local="130934379363523098" remote="130934020200000000" Dst="1" />
<file name="progress-white-bg.gif" server="ftp.bennettcodes.com" local="130934379362314270" remote="130934020200000000" Dst="1" />
</dwsync>